doc_note_untangler/__init__.py
doc_note_untangler/build.py
doc_note_untangler/cli.py
doc_note_untangler-1.0.1.dist-info/LICENSE
doc_note_untangler-1.0.1.dist-info/WHEEL
doc_note_untangler-1.0.1.dist-info/METADATA
doc_note_untangler-1.0.1.dist-info/RECORD
