Metadata-Version: 2.1
Name: doc-note-untangler
Version: 1.0.1
Summary: Untangle special markdown blocks from docstrings and assemble them into a static webpage.
Home-page: https://github.com/msladecek/doc_note_untangler
License: Unlicense
Keywords: markdown,documentation,static page
Author: msladecek
Author-email: martin.sladecek@gmail.com
Requires-Python: >=3.8,<4.0
Classifier: License :: OSI Approved :: The Unlicense (Unlicense)
Classifier: License :: Other/Proprietary License
Classifier: Programming Language :: Python :: 3
Classifier: Programming Language :: Python :: 3.8
Classifier: Programming Language :: Python :: 3.9
Requires-Dist: Markdown (>=3.3.4,<4.0.0)
Requires-Dist: Pygments (>=2.8.1,<3.0.0)
Requires-Dist: md-mermaid (>=0.1.1,<0.2.0)
Project-URL: Repository, https://github.com/msladecek/doc_note_untangler
